Pymote-0.2.2.dist-info/DESCRIPTION.rst
Pymote-0.2.2.dist-info/METADATA
Pymote-0.2.2.dist-info/RECORD
Pymote-0.2.2.dist-info/WHEEL
Pymote-0.2.2.dist-info/entry_points.txt
Pymote-0.2.2.dist-info/metadata.json
Pymote-0.2.2.dist-info/top_level.txt
pymote/__init__.py
pymote/algorithm.py
pymote/channeltype.py
pymote/environment.py
pymote/logger.py
pymote/message.py
pymote/network.py
pymote/networkgenerator.py
pymote/node.py
pymote/npickle.py
pymote/release.py
pymote/sensor.py
pymote/simulation.py
pymote/algorithms/__init__.py
pymote/algorithms/broadcast.py
pymote/algorithms/readsensors.py
pymote/algorithms/niculescu2003/__init__.py
pymote/algorithms/niculescu2003/dvhop.py
pymote/algorithms/niculescu2003/floodingupdate.py
pymote/algorithms/niculescu2003/trilaterate.py
pymote/conf/__init__.py
pymote/conf/global_settings.py
pymote/conf/ipython/__init__.py
pymote/conf/ipython/ipython_config.py
pymote/conf/ipython/ipython_notebook_config.py
pymote/gui/__init__.py
pymote/gui/dictionarytreemodel.py
pymote/gui/icons_rc.py
pymote/gui/qtreeview_example.py
pymote/gui/simulation.ui.py
pymote/gui/simulationgui.py
pymote/gui/simulationui.py
pymote/scripts/__init__.py
pymote/scripts/ipymote.py
pymote/tests/__init__.py
pymote/tests/test_algorithm.py
pymote/tests/test_network.py
pymote/tests/test_networkgenerator.py
pymote/tests/test_sensor.py
pymote/tests/test_stitchers.py
pymote/utils/__init__.py
pymote/utils/helpers.py
pymote/utils/tree.py
pymote/utils/visualization.py
pymote/utils/localization/__init__.py
pymote/utils/localization/aoastitcher.py
pymote/utils/localization/basestitcher.py
pymote/utils/localization/diststitcher.py
pymote/utils/localization/helpers.py
pymote/utils/localization/stitchsubclusterselectors.py
pymote/utils/memory/__init__.py
pymote/utils/memory/positions.py
