Metadata-Version: 1.1
Name: Pymote
Version: 0.2.2
Summary: A high-level Python library for simulation of distributed algorithms.
Home-page: https://github.com/darbula/pymote
Author: Damir Arbula
Author-email: damir.arbula@gmail.com
License: BSD
Keywords: Networks,Distributed algorithms
Platform: Windows
Platform: Linux
Platform: Mac OSX
Classifier: Development Status :: 3 - Alpha
Classifier: Intended Audience :: Developers
Classifier: Intended Audience :: Science/Research
Classifier: License :: OSI Approved :: BSD License
Classifier: Operating System :: OS Independent
Classifier: Programming Language :: Python :: 2
Classifier: Programming Language :: Python :: 2.6
Classifier: Programming Language :: Python :: 2.7
Classifier: Topic :: Software Development :: Libraries :: Python Modules
Classifier: Topic :: System :: Distributed Computing
Classifier: Topic :: System :: Networking
Classifier: Topic :: Scientific/Engineering :: Information Analysis
